pyhs3ng/__init__.py
pyhs3ng/const.py
pyhs3ng/device.py
pyhs3ng/errors.py
pyhs3ng/events.py
pyhs3ng/factory.py
pyhs3ng/helpers.py
pyhs3ng/hometroller.py
pyhs3ng/insteon.py
pyhs3ng/listener.py
pyhs3ng/zwave.py
pyhs3ng-1.0.8.dist-info/LICENSE
pyhs3ng-1.0.8.dist-info/METADATA
pyhs3ng-1.0.8.dist-info/WHEEL
pyhs3ng-1.0.8.dist-info/top_level.txt
pyhs3ng-1.0.8.dist-info/RECORD
